bchess/__init__.py
bchess/__main__.py
bchess/bchess.py
bchess/book.py
bchess/ecodb.py
bchess/engine.py
bchess/imui.py
bchess/data/bchess.conf
bchess/data/default.nnue
bchess/data/default.small.nnue
bchess/data/maia-1100.pb.gz
bchess/data/maia-1300.pb.gz
bchess/data/maia-1500.pb.gz
bchess/data/maia-1700.pb.gz
bchess/data/maia-1900.pb.gz
bchess/data/meangirl-8.pb.gz
bchess/data/tinygyal-8.pb.gz
build/Stockfish-sf_17.1.tar.gz
build/lc0-0.31.2.tar.gz
build/lczero-common.tar.gz
build/lc0deps/eigen-3.4.0.tar.bz2
build/lc0deps/eigen_3.4.0-1_patch.zip
build/lc0deps/zlib-1.2.11-4-wrap.zip
build/lc0deps/zlib-1.2.11.tar.gz
bchess/data/openings.sqlite
bchess/data/stockfish
bchess/data/lc0
bchess-0.0.10.dist-info/METADATA
bchess-0.0.10.dist-info/WHEEL
bchess-0.0.10.dist-info/entry_points.txt
bchess-0.0.10.dist-info/RECORD