Metadata-Version: 2.1
Name: bchess
Version: 0.0.10
Summary: Beginner-friendly offline chess in a console, with batteries included.
Requires-Python: >=3.6
License: GPLv3+
Author: Vitaly Magerya
Classifier: Development Status :: 3 - Alpha
Classifier: Environment :: Console
Classifier: License :: OSI Approved :: GNU General Public License v3 or later (GPLv3+)
Classifier: Natural Language :: English
Classifier: Operating System :: Unix
Classifier: Programming Language :: Python :: 3
Classifier: Topic :: Games/Entertainment :: Board Games
Home-Page: https://github.com/magv/bchess
Requires-Dist: python-chess>=0.31
